simplecolorlogger/__init__.py
simplecolorlogger/logger.py
SimpleColorLogger-1.4.1.dist-info/METADATA
SimpleColorLogger-1.4.1.dist-info/WHEEL
SimpleColorLogger-1.4.1.dist-info/top_level.txt
SimpleColorLogger-1.4.1.dist-info/RECORD
