Metadata-Version: 2.1
Name: SimpleColorLogger
Version: 1.4.1
Summary: A simple colored logger for terminal output
Home-page: https://github.com/timlukastlt/SimpleColorLogger
Author: Tim Lukas Tritschler
Author-email: info@music-request.com
Classifier: Programming Language :: Python :: 3
Classifier: License :: OSI Approved :: MIT License
Classifier: Operating System :: OS Independent
Requires-Python: >=3.6
